{
"type": "FeatureCollection",
"name": "arte_xavega",
"crs": { "type": "name", "properties": { "name": "urn:ogc:def:crs:OGC:1.3:CRS84" } },
"features": [
{ "type": "Feature", "properties": { "id": null, "loc": "Torreira" }, "geometry": { "type": "Point", "coordinates": [ -8.712010261226908, 40.766392278641995 ] } },
{ "type": "Feature", "properties": { "id": null, "loc": "Vagueira" }, "geometry": { "type": "Point", "coordinates": [ -8.771227030211556, 40.555462678700088 ] } },
{ "type": "Feature", "properties": { "id": null, "loc": "Areão" }, "geometry": { "type": "Point", "coordinates": [ -8.780249904277998, 40.522923152058645 ] } }
]
}
